keyrock_flask/__init__.py
keyrock_flask/flask_util/__init__.py
keyrock_flask/flask_util/batch.py
keyrock_flask/flask_util/exc.py
keyrock_flask/flask_util/reloadable_app.py
keyrock_flask/flask_util/test_flask_util.py
keyrock_flask/flask_util/token.py
keyrock_flask-2024.2.15.1117.dist-info/METADATA
keyrock_flask-2024.2.15.1117.dist-info/WHEEL
keyrock_flask-2024.2.15.1117.dist-info/top_level.txt
keyrock_flask-2024.2.15.1117.dist-info/RECORD
