Metadata-Version: 2.1
Name: keyrock-flask
Version: 2024.2.15.1117
Requires-Dist: keyrock-core
Requires-Dist: keyrock-encryption
Requires-Dist: flask ==3.0.2
Requires-Dist: redis ==5.0.1
Requires-Dist: requests ==2.31.0
